MANIFEST.in
README.rst
bootstrap-buildout.py
buildout.cfg
requirements.txt
setup.py
version.txt
bob/__init__.py
bob.db.cbsr_nir_vis_2.egg-info/PKG-INFO
bob.db.cbsr_nir_vis_2.egg-info/SOURCES.txt
bob.db.cbsr_nir_vis_2.egg-info/dependency_links.txt
bob.db.cbsr_nir_vis_2.egg-info/entry_points.txt
bob.db.cbsr_nir_vis_2.egg-info/not-zip-safe
bob.db.cbsr_nir_vis_2.egg-info/requires.txt
bob.db.cbsr_nir_vis_2.egg-info/top_level.txt
bob/db/__init__.py
bob/db/cbsr_nir_vis_2/__init__.py
bob/db/cbsr_nir_vis_2/create.py
bob/db/cbsr_nir_vis_2/driver.py
bob/db/cbsr_nir_vis_2/models.py
bob/db/cbsr_nir_vis_2/query.py
bob/db/cbsr_nir_vis_2/test.py
doc/conf.py
doc/guide.rst
doc/index.rst
doc/py_api.rst