Metadata-Version: 1.1
Name: bob.db.cbsr-nir-vis-2
Version: 2.0.7
Summary: CASIA NIR-VIS 2.0 Face Database protocol
Home-page: https://gitlab.idiap.ch/biometric/bob.db.cbsr_nir_vis_2
Author: Tiago de Freitas Pereira
Author-email: tiago.pereira@idiap.ch
License: BSD
Platform: UNKNOWN
Classifier: Framework :: Bob
Classifier: Development Status :: 5 - Production/Stable
Classifier: Intended Audience :: Education
Classifier: License :: OSI Approved :: BSD License
Classifier: Natural Language :: English
Classifier: Programming Language :: Python
Classifier: Programming Language :: Python :: 3
Classifier: Topic :: Scientific/Engineering :: Artificial Intelligence
Classifier: Topic :: Database :: Front-Ends
